setup.py
cron_runner.egg-info/PKG-INFO
cron_runner.egg-info/SOURCES.txt
cron_runner.egg-info/dependency_links.txt
cron_runner.egg-info/entry_points.txt
cron_runner.egg-info/requires.txt
cron_runner.egg-info/top_level.txt
cronrunner/__init__.py
cronrunner/base.py
cronrunner/config.py
cronrunner/cron.py
cronrunner/database.py
cronrunner/filelock.py
cronrunner/main.py
cronrunner/notification.py
cronrunner/registry.py