Metadata-Version: 1.0
Name: cron-runner
Version: 0.0.2
Summary: Runner of cron jobs with logging and duration timing
Home-page: https://github.com/marijngiesen/cron-runner
Author: Marijn Giesen
Author-email: marijn@studio-donder.nl
License: Apache 2.0
Platform: UNKNOWN
